cachememo/__init__.py
cachememo/cache.py
cachememo/clocks.py
cachememo/keys.py
cachememo/locks.py
cachememo/memoize.py
cachememo/types.py
cachememo-0.1.2.dist-info/licenses/LICENSE 
cachememo-0.1.2.dist-info/METADATA
cachememo-0.1.2.dist-info/WHEEL
cachememo-0.1.2.dist-info/top_level.txt
cachememo-0.1.2.dist-info/RECORD
