Metadata-Version: 2.4
Name: cachememo
Version: 0.1.2
Summary: TTL memoization for sync/async functions with stampede protection
Author: Fatemeh
Requires-Python: >=3.10
License-File: LICENSE 
Provides-Extra: dev
Requires-Dist: pytest>=7.0; extra == "dev"
Requires-Dist: pytest-asyncio>=0.23; extra == "dev"
Dynamic: license-file
